{"data":{"responsecode":"000","responsemsg":"","quote":{"hi":"9.500","rs_stock_flag":false,"fiscal_year_end":"2024年12月31日","hist_closedate":"2025年9月25日","replication_method":null,"amt_os":"1,222,000,000","primaryexch":"香港交易所","ric":"0177.HK","product_subtype":null,"db_updatetime":"2025年9月28日08:06","mkt_cap_u":"B","am_u":"M","ew_sub_right":"","secondary_listing":false,"ew_amt_os_cur":null,"ccy":"HKD","management_fee":"","ew_underlying_code":null,"trdstatus":"N","nav":"","original_offer_price":"","issue":"","asset_class":null,"eps":0.9819,"inline_upper_strike_price":"","sedol":"6005504","am":"64.99","iv":"","ew_strike":"","as":"9.370","geographic_focus":null,"incorpin":"中華人民共和國","etp_baseCur":null,"ew_amt_os":"","bd":"9.360","registrar":"香港中央證券登記有限公司","depositary":null,"exotic_type":null,"callput_indicator":null,"primary_market":null,"underlying_index":null,"lot":"2,000","update_time":"2025-09-28 00:06:03.0","lo52":"7.560","shares_issued_date":"2025年8月31日","premium":"","strike_price_ccy":null,"yield":"","vo_u":"M","base_currency":null,"coupon":"","expiry_date":"","chairman":null,"underlying_ric":"600377.SS","hi52":"11.660","issuer_name":"江蘇寧滬高速公路股份有限公司 - H股","h_share_flag":true,"ew_sub_per_from":"","div_yield":"5.73","interest_payment_date":"-","updatetime":"2025年9月26日16:08","aum_date":"","lo":"9.280","mkt_cap":"11.45","f_aum_hkd":null,"ew_sub_per_to":"","ls":"9.370","nav_date":"","csic_classification":"工業","floating_flag":false,"issued_shares_note":null,"nom_ccy":null,"eff_gear":"","board_lot_nominal":null,"hsic_ind_classification":"工業 - 工用運輸","ew_desc":null,"inception_date":"","nc":"-0.090","aum":"","issued_shares_class_B":null,"vo":"6.94","secondary_listing_flag":false,"listing_date":"1997年6月27日","issued_shares_class_A":null,"as_at_label":"截至","ew_amt_os_dat":"","nm":"江蘇寧滬高速公路股份有限公司 - H股","nm_s":"江蘇寧滬高速公路","sym":"177","inline_lower_strike_price":"","listing_category":"主要上市","ew_strike_cur":null,"exotic_warrant_indicator":null,"investment_focus":null,"call_price":"","tck":"0.010","strike_price":"","summary":"江蘇寧滬高速公路股份有限公司是一家主要從事收費路橋的投資、建設、經營及管理業務的中國公司。該公司主要從事滬寧高速、寧常高速和鎮溧高速、廣靖高速和錫澄高速、錫宜高速和無錫環太湖公路、鎮丹高速、五峰山大橋、常宜高速、宜長高速、龍潭大橋、錫太高速及丹金高速的經營及管理業務等。該公司還提供配套服務包括高速公路服務區的加油，餐飲，零售業務。該公司還從事房地產開發、電力銷售、廣告及其他。該公司主要在國內市場開展其業務。","op":"9.500","aum_u":"","nav_ccy":null,"class_B_description":null,"os":"","wnt_gear":"","transfer_of_listing_date":"","hsic_sub_sector_classification":"鐵路及公路","amt_ccy":null,"class_A_description":null,"domicile_country":null,"entitlement_ratio":"","product_type":"EQTY","office_address":"中國<br/>南京市<br/>仙林大道6號","pc":"-0.95","days_to_expiry":null,"underlying_code":null,"pe":"9.03","eps_ccy":"RMB","hdr":false,"launch_date":"","hc":"9.460","isin":"CNE1000003J5","moneyness":""}},"qid":"1759074187600"}
