{"data":{"responsecode":"000","responsemsg":"","quote":{"hi":"1.410","rs_stock_flag":false,"fiscal_year_end":"2025年3月31日","hist_closedate":"2025年9月25日","replication_method":null,"amt_os":"1,256,197,771","primaryexch":"香港交易所","ric":"1830.HK","product_subtype":null,"db_updatetime":"2025年9月28日08:06","mkt_cap_u":"B","am_u":"K","ew_sub_right":"","secondary_listing":false,"ew_amt_os_cur":null,"ccy":"HKD","management_fee":"","ew_underlying_code":null,"trdstatus":"N","nav":"","original_offer_price":"","issue":"","asset_class":null,"eps":0.1647,"inline_upper_strike_price":"","sedol":"B7F0L00","am":"530.29","iv":"","ew_strike":"","as":"1.400","geographic_focus":null,"incorpin":"開曼群島","etp_baseCur":null,"ew_amt_os":"","bd":"1.390","registrar":"卓佳證券登記有限公司","depositary":null,"exotic_type":null,"callput_indicator":null,"primary_market":null,"underlying_index":null,"lot":"1,000","update_time":"2025-09-28 00:06:03.0","lo52":"1.390","shares_issued_date":"2025年8月31日","premium":"","strike_price_ccy":null,"yield":"","vo_u":"K","base_currency":null,"coupon":"","expiry_date":"","chairman":"歐陽江","underlying_ric":"1830.HK","hi52":"3.149","issuer_name":"完美醫療健康管理有限公司","h_share_flag":false,"ew_sub_per_from":"","div_yield":"11.86","interest_payment_date":"-","updatetime":"2025年9月26日16:08","aum_date":"","lo":"1.390","mkt_cap":"1.75","f_aum_hkd":null,"ew_sub_per_to":"","ls":"1.400","nav_date":"","csic_classification":null,"floating_flag":false,"issued_shares_note":null,"nom_ccy":null,"eff_gear":"","board_lot_nominal":null,"hsic_ind_classification":"醫療保健業 - 其他醫療保健","ew_desc":null,"inception_date":"","nc":"-0.010","aum":"","issued_shares_class_B":null,"vo":"379.00","secondary_listing_flag":false,"listing_date":"2012年2月10日","issued_shares_class_A":null,"as_at_label":"截至","ew_amt_os_dat":"","nm":"完美醫療健康管理有限公司","nm_s":"完美醫療","sym":"1830","inline_lower_strike_price":"","listing_category":"主要上市","ew_strike_cur":null,"exotic_warrant_indicator":null,"investment_focus":null,"call_price":"","tck":"0.010","strike_price":"","summary":"完美醫療健康管理有限公司是一家主要從事提供醫療健康及醫療美容服務的投資控股公司。該公司從事提供男士及女士的個人化醫美方案等醫療美容服務。該公司還從事提供生髮醫療服務、痛癥醫療服務、預防醫療服務等醫療健康服務。此外，該公司還從事提供不育、人工受孕及冷凍卵子服務、產前診斷服務、婦產科醫療服務及婦女癌癥及健康管理服務等生殖醫療服務。該公司主要在香港、澳門、中國大陸、澳洲及新加坡經營業務。","op":"1.400","aum_u":"","nav_ccy":null,"class_B_description":null,"os":"","wnt_gear":"","transfer_of_listing_date":"","hsic_sub_sector_classification":"醫療及醫學美容服務","amt_ccy":null,"class_A_description":null,"domicile_country":null,"entitlement_ratio":"","product_type":"EQTY","office_address":"香港九龍旺角<br/>亞皆老街8號<br/>朗豪坊辨公室大樓<br/>51樓","pc":"-0.71","days_to_expiry":null,"underlying_code":null,"pe":"8.50","eps_ccy":"HKD","hdr":false,"launch_date":"","hc":"1.410","isin":"KYG7013H1056","moneyness":""}},"qid":"1759074800368"}
