{"data":{"responsecode":"000","responsemsg":"","quote":{"hi":"2.410","rs_stock_flag":false,"fiscal_year_end":"2024年12月31日","hist_closedate":"2025年9月25日","replication_method":null,"amt_os":"3,700,891,382","primaryexch":"香港交易所","ric":"1883.HK","product_subtype":null,"db_updatetime":"2025年9月28日08:06","mkt_cap_u":"B","am_u":"M","ew_sub_right":"","secondary_listing":false,"ew_amt_os_cur":null,"ccy":"HKD","management_fee":"","ew_underlying_code":null,"trdstatus":"N","nav":"","original_offer_price":"","issue":"","asset_class":null,"eps":0.2459,"inline_upper_strike_price":"","sedol":"B1VKZ88","am":"12.87","iv":"","ew_strike":"","as":"2.400","geographic_focus":null,"incorpin":"香港","etp_baseCur":null,"ew_amt_os":"","bd":"2.390","registrar":"卓佳證券登記有限公司","depositary":null,"exotic_type":null,"callput_indicator":null,"primary_market":null,"underlying_index":null,"lot":"1,000","update_time":"2025-09-28 00:06:03.0","lo52":"2.130","shares_issued_date":"2025年8月31日","premium":"","strike_price_ccy":null,"yield":"","vo_u":"M","base_currency":null,"coupon":"","expiry_date":"","chairman":"羅西成","underlying_ric":"1883.HK","hi52":"2.640","issuer_name":"中信國際電訊集團有限公司","h_share_flag":false,"ew_sub_per_from":"","div_yield":"7.83","interest_payment_date":"-","updatetime":"2025年9月26日16:08","aum_date":"","lo":"2.390","mkt_cap":"8.88","f_aum_hkd":null,"ew_sub_per_to":"","ls":"2.400","nav_date":"","csic_classification":null,"floating_flag":false,"issued_shares_note":null,"nom_ccy":null,"eff_gear":"","board_lot_nominal":null,"hsic_ind_classification":"電訊業 - 電訊","ew_desc":null,"inception_date":"","nc":"0.000","aum":"","issued_shares_class_B":null,"vo":"5.36","secondary_listing_flag":false,"listing_date":"2007年4月3日","issued_shares_class_A":null,"as_at_label":"截至","ew_amt_os_dat":"","nm":"中信國際電訊集團有限公司","nm_s":"中信國際電訊","sym":"1883","inline_lower_strike_price":"","listing_category":"主要上市","ew_strike_cur":null,"exotic_warrant_indicator":null,"investment_focus":null,"call_price":"","tck":"0.010","strike_price":"","summary":"中信國際電訊集團有限公司是一家主要從事提供電信服務業務的投資控股公司。該公司是一家互聯網化綜合電訊企業，主要提供移動通訊服務、互聯網業務、國際電信業務、企業業務及固話語音業務。該公司還從事銷售移動電話手機及設備業務。此外，該公司還通過其子公司還從事提供增值電信服務業務。","op":"2.400","aum_u":"","nav_ccy":null,"class_B_description":null,"os":"","wnt_gear":"","transfer_of_listing_date":"","hsic_sub_sector_classification":"電訊服務","amt_ccy":null,"class_A_description":null,"domicile_country":null,"entitlement_ratio":"","product_type":"EQTY","office_address":"香港新界葵涌<br/>葵福路93號<br/>中信電訊大廈25樓","pc":"0.00","days_to_expiry":null,"underlying_code":null,"pe":"9.76","eps_ccy":"HKD","hdr":false,"launch_date":"","hc":"2.400","isin":"HK1883037637","moneyness":""}},"qid":"1759074363658"}
