{"data":{"responsecode":"000","responsemsg":"","quote":{"hi":"","rs_stock_flag":false,"fiscal_year_end":"30 Apr 2025","hist_closedate":"25 Sep 2025","replication_method":null,"amt_os":"800,000,000","primaryexch":"HKEX","ric":"1470.HK","product_subtype":null,"db_updatetime":"26 Sep 2025 18:38","mkt_cap_u":"M","am_u":"","ew_sub_right":"","secondary_listing":false,"ew_amt_os_cur":null,"ccy":"HKD","management_fee":"","ew_underlying_code":null,"trdstatus":"N","nav":"","original_offer_price":"","issue":"","asset_class":null,"eps":0.0068,"inline_upper_strike_price":"","sedol":"BD1FX16","am":"","iv":"","ew_strike":"","as":"0.134","geographic_focus":null,"incorpin":"Cayman Islands","etp_baseCur":null,"ew_amt_os":"","bd":"0.117","registrar":"Boardroom Share Registrars (HK) Ltd.","depositary":null,"exotic_type":null,"callput_indicator":null,"primary_market":null,"underlying_index":null,"lot":"4,000","update_time":"2025-09-26 10:38:37.0","lo52":"0.032","shares_issued_date":"31 Aug 2025","premium":"","strike_price_ccy":null,"yield":"","vo_u":"","base_currency":null,"coupon":"","expiry_date":"","chairman":"Liu Guoqing","underlying_ric":"1470.HK","hi52":"0.340","issuer_name":"Prosper One International Holdings Co. Ltd.","h_share_flag":false,"ew_sub_per_from":"","div_yield":"","interest_payment_date":"-","updatetime":"26 Sep 2025 13:02","aum_date":"","lo":"","mkt_cap":"101.60","f_aum_hkd":null,"ew_sub_per_to":"","ls":"0.127","nav_date":"","csic_classification":null,"floating_flag":false,"issued_shares_note":null,"nom_ccy":null,"eff_gear":"","board_lot_nominal":null,"hsic_ind_classification":"Materials - Basic Materials","ew_desc":null,"inception_date":"","nc":"0.000","aum":"","issued_shares_class_B":null,"vo":"","secondary_listing_flag":false,"listing_date":"12 May 2015","issued_shares_class_A":null,"as_at_label":"as at","ew_amt_os_dat":"","nm":"Prosper One International Holdings Co. Ltd.","nm_s":"PROSPER ONE","sym":"1470","inline_lower_strike_price":"","listing_category":"Primary Listing","ew_strike_cur":null,"exotic_warrant_indicator":null,"investment_focus":null,"call_price":"","tck":"0.001","strike_price":"","summary":"Prosper One International Holdings Company Ltd, formerly Tic Tac International Holdings Company Ltd is an investment holding company principally engaged in retailing watches. The Company operates through three business segments. Retail Business of Watches segment is principally engaged in retail of multi brands of watches in Hong Kong. Wholesale Business of Watches segment is mainly engaged in the wholesale of multi brands of watches in Hong Kong. Trading of Fertilisers and Other Related Products segment is engaged in provision of agency services in relation to trading of fertilisers and other related products. Manufacture and Sales of Compound Fertilisers segment is mainly engaged in the manufacture and sales of compound fertilisers in the People’s Republic of China.","op":"","aum_u":"","nav_ccy":null,"class_B_description":null,"os":"","wnt_gear":"","transfer_of_listing_date":"","hsic_sub_sector_classification":"Fertilisers & Agricultural Chemicals","amt_ccy":null,"class_A_description":null,"domicile_country":null,"entitlement_ratio":"","product_type":"EQTY","office_address":"Room 4801, 48/F<br/>Hopewell Centre<br/>No. 183 Queen's Road East<br/>Wanchai, Hong Kong","pc":"0.00","days_to_expiry":null,"underlying_code":null,"pe":"18.68","eps_ccy":"HKD","hdr":false,"launch_date":"","hc":"0.127","isin":"KYG7280T1058","moneyness":""}},"qid":"1758891564036"}
